estimated_taxes/__init__.py
estimated_taxes/__main__.py
estimated_taxes/__version__.py
estimated_taxes/argument_parser.py
estimated_taxes/calculator.py
estimated_taxes/formatter.py
estimated_taxes/loader.py
estimated_taxes/model.py
estimated_taxes/constants/__init__.py
estimated_taxes/constants/ca.py
estimated_taxes/constants/fed.py
estimated_taxes/constants/util.py
estimated_taxes-2025.2.dist-info/licenses/LICENSE.txt
estimated_taxes-2025.2.dist-info/METADATA
estimated_taxes-2025.2.dist-info/WHEEL
estimated_taxes-2025.2.dist-info/entry_points.txt
estimated_taxes-2025.2.dist-info/top_level.txt
estimated_taxes-2025.2.dist-info/RECORD
