Metadata-Version: 2.4
Name: estimated-taxes
Version: 2025.2
Summary: Estimated taxes calculator
Home-page: https://github.com/nkouevda/estimated-taxes
Author: Nikita Kouevda
Author-email: nkouevda@gmail.com
License: MIT
License-File: LICENSE.txt
Requires-Dist: pyyaml
Dynamic: author
Dynamic: author-email
Dynamic: description
Dynamic: description-content-type
Dynamic: home-page
Dynamic: license
Dynamic: license-file
Dynamic: requires-dist
Dynamic: summary
